notifyall/__init__.py
notifyall/exceptions.py
notifyall/notification_manager.py
notifyall/notifyall.py
notifyall/notifiers/__init__.py
notifyall/notifiers/base_notifier.py
notifyall/notifiers/sns_notifier.py
notifyall/notifiers/telegram_notifier.py
notifyall/params/__init__.py
notifyall/params/sns_params.py
notifyall/params/telegram_params.py
tests/__init__.py
tests/notifyall_test.py
notifyall-1.0.dist-info/LICENSE
notifyall-1.0.dist-info/METADATA
notifyall-1.0.dist-info/WHEEL
notifyall-1.0.dist-info/top_level.txt
notifyall-1.0.dist-info/RECORD
