Metadata-Version: 2.1
Name: notifyall
Version: 1.0
Summary: A multi-channel notification library
Home-page: https://github.com/gibran-toriz/lalakiri-notification-library.git
Author: Laura Mendez
Author-email: malaura_404@hotmail.com
License-File: LICENSE
Requires-Dist: PyYAML ==6.0.1
Requires-Dist: boto3 ==1.29.3
Requires-Dist: botocore ==1.32.3
Requires-Dist: requests ==2.31.0
Requires-Dist: requests-toolbelt ==1.0.0
